worksforme/__init__.py
worksforme/main.py
worksforme/version.py
worksforme/templates/base.html
worksforme/templates/script.js
worksforme/templates/style.css
worksforme-0.2.0.dist-info/LICENSE
worksforme-0.2.0.dist-info/METADATA
worksforme-0.2.0.dist-info/WHEEL
worksforme-0.2.0.dist-info/entry_points.txt
worksforme-0.2.0.dist-info/top_level.txt
worksforme-0.2.0.dist-info/RECORD
