Metadata-Version: 2.1
Name: worksforme
Version: 0.2.0
Summary: A primitive browser-based soundboard
Home-page: https://vonshednob.cc/
Author: R
Author-email: contact+worksforme@vonshednob.cc
License: MIT
Platform: UNKNOWN
Requires-Python: >=3.6
License-File: LICENSE
Requires-Dist: bottle
